lightcurve_fitting/__init__.py
lightcurve_fitting/_version.py
lightcurve_fitting/bolometric.py
lightcurve_fitting/filters.py
lightcurve_fitting/fitting.py
lightcurve_fitting/lightcurve.py
lightcurve_fitting/models.py
lightcurve_fitting/serif.mplstyle
lightcurve_fitting/speccal.py
lightcurve_fitting/example/SN2016bkv.txt
lightcurve_fitting/filters/ATLAS_cyan.txt
lightcurve_fitting/filters/ATLAS_orange.txt
lightcurve_fitting/filters/CTIO_DECam.Y.dat
lightcurve_fitting/filters/CTIO_DECam.g.dat
lightcurve_fitting/filters/CTIO_DECam.i.dat
lightcurve_fitting/filters/CTIO_DECam.r.dat
lightcurve_fitting/filters/CTIO_DECam.z.dat
lightcurve_fitting/filters/GAIA_GAIA0.G.dat
lightcurve_fitting/filters/GALEX_GALEX.FUV.dat
lightcurve_fitting/filters/GALEX_GALEX.NUV.dat
lightcurve_fitting/filters/Gemini_Flamingos2.H.dat
lightcurve_fitting/filters/Gemini_Flamingos2.J.dat
lightcurve_fitting/filters/Gemini_Flamingos2.Ks.dat
lightcurve_fitting/filters/Generic_Cousins.I.dat
lightcurve_fitting/filters/Generic_Cousins.R.dat
lightcurve_fitting/filters/Generic_Johnson.B.dat
lightcurve_fitting/filters/Generic_Johnson.U.dat
lightcurve_fitting/filters/Generic_Johnson.V.dat
lightcurve_fitting/filters/JWST_MIRI.F1000W.dat
lightcurve_fitting/filters/JWST_MIRI.F1130W.dat
lightcurve_fitting/filters/JWST_MIRI.F1280W.dat
lightcurve_fitting/filters/JWST_MIRI.F1500W.dat
lightcurve_fitting/filters/JWST_MIRI.F1800W.dat
lightcurve_fitting/filters/JWST_MIRI.F2100W.dat
lightcurve_fitting/filters/JWST_MIRI.F2550W.dat
lightcurve_fitting/filters/JWST_MIRI.F560W.dat
lightcurve_fitting/filters/JWST_MIRI.F770W.dat
lightcurve_fitting/filters/JWST_NIRCam.F070W.dat
lightcurve_fitting/filters/JWST_NIRCam.F090W.dat
lightcurve_fitting/filters/JWST_NIRCam.F115W.dat
lightcurve_fitting/filters/JWST_NIRCam.F150W.dat
lightcurve_fitting/filters/JWST_NIRCam.F182M.dat
lightcurve_fitting/filters/JWST_NIRCam.F200W.dat
lightcurve_fitting/filters/JWST_NIRCam.F250M.dat
lightcurve_fitting/filters/JWST_NIRCam.F277W.dat
lightcurve_fitting-0.10.0.dist-info/LICENSE
lightcurve_fitting-0.10.0.dist-info/METADATA
lightcurve_fitting-0.10.0.dist-info/WHEEL
lightcurve_fitting-0.10.0.dist-info/top_level.txt
lightcurve_fitting-0.10.0.dist-info/RECORD
