Metadata-Version: 2.1
Name: lightcurve-fitting
Version: 0.10.0
Summary: Tools to fit analytical models to multiband light curves of astronomical transients
Home-page: https://github.com/griffin-h/lightcurve_fitting
Author: Griffin Hosseinzadeh
Author-email: griffin0@arizona.edu
License: GNU General Public License v3 (GPLv3)
Classifier: Development Status :: 2 - Pre-Alpha
Classifier: Natural Language :: English
Classifier: Programming Language :: Python :: 3
Requires-Python: >=3.6
License-File: LICENSE
Requires-Dist: numpy
Requires-Dist: matplotlib
Requires-Dist: emcee (>=3.1.1)
Requires-Dist: corner
Requires-Dist: astropy (>=5)
Requires-Dist: scipy
Requires-Dist: extinction
